repeat_text.py
repeat_text-0.1.5.dist-info/METADATA
repeat_text-0.1.5.dist-info/WHEEL
repeat_text-0.1.5.dist-info/entry_points.txt
repeat_text-0.1.5.dist-info/top_level.txt
repeat_text-0.1.5.dist-info/RECORD
