Metadata-Version: 2.1
Name: repeat-text
Version: 0.1.5
Requires-Dist: termcolor
